.gitignore
.travis.yml
README.md
pylint.rc
requirements.txt
setup.py
docs/conf.py
docs/index.rst
docs/iqoptionapi.http.rst
docs/iqoptionapi.rst
docs/iqoptionapi.ws.chanels.rst
docs/iqoptionapi.ws.objects.rst
docs/iqoptionapi.ws.rst
docs/modules.rst
iqoptionapi/__init__.py
iqoptionapi/api.py
iqoptionapi/constants.py
iqoptionapi.egg-info/PKG-INFO
iqoptionapi.egg-info/SOURCES.txt
iqoptionapi.egg-info/dependency_links.txt
iqoptionapi.egg-info/not-zip-safe
iqoptionapi.egg-info/top_level.txt
iqoptionapi/http/__init__.py
iqoptionapi/http/appinit.py
iqoptionapi/http/auth.py
iqoptionapi/http/billing.py
iqoptionapi/http/buyback.py
iqoptionapi/http/changebalance.py
iqoptionapi/http/getprofile.py
iqoptionapi/http/getregdata.py
iqoptionapi/http/login.py
iqoptionapi/http/loginv2.py
iqoptionapi/http/profile.py
iqoptionapi/http/register.py
iqoptionapi/http/resource.py
iqoptionapi/http/token.py
iqoptionapi/ws/__init__.py
iqoptionapi/ws/client.py
iqoptionapi/ws/chanels/__init__.py
iqoptionapi/ws/chanels/base.py
iqoptionapi/ws/chanels/buyback.py
iqoptionapi/ws/chanels/buyv2.py
iqoptionapi/ws/chanels/candles.py
iqoptionapi/ws/chanels/setactives.py
iqoptionapi/ws/chanels/ssid.py
iqoptionapi/ws/chanels/subscribe.py
iqoptionapi/ws/chanels/unsubscribe.py
iqoptionapi/ws/objects/__init__.py
iqoptionapi/ws/objects/base.py
iqoptionapi/ws/objects/candles.py
iqoptionapi/ws/objects/profile.py
iqoptionapi/ws/objects/timesync.py
iqoptionapi/http/__init__.py
iqoptionapi/http/appinit.py
iqoptionapi/http/auth.py
iqoptionapi/http/billing.py
iqoptionapi/http/buyback.py
iqoptionapi/http/changebalance.py
iqoptionapi/http/getprofile.py
iqoptionapi/http/getregdata.py
iqoptionapi/http/login.py
iqoptionapi/http/loginv2.py
iqoptionapi/http/profile.py
iqoptionapi/http/register.py
iqoptionapi/http/resource.py
iqoptionapi/http/token.py
iqoptionapi/ws/__init__.py
iqoptionapi/ws/client.py
iqoptionapi/ws/chanels/__init__.py
iqoptionapi/ws/chanels/base.py
iqoptionapi/ws/chanels/buyback.py
iqoptionapi/ws/chanels/buyv2.py
iqoptionapi/ws/chanels/candles.py
iqoptionapi/ws/chanels/setactives.py
iqoptionapi/ws/chanels/ssid.py
iqoptionapi/ws/chanels/subscribe.py
